discord_user_history/HistoryService.py
discord_user_history/User.py
discord_user_history/Validation.py
discord_user_history/__init__.py
discord_user_history-0.0.3.dist-info/LICENSE
discord_user_history-0.0.3.dist-info/METADATA
discord_user_history-0.0.3.dist-info/WHEEL
discord_user_history-0.0.3.dist-info/top_level.txt
discord_user_history-0.0.3.dist-info/RECORD
