Metadata-Version: 2.1
Name: discord-user-history
Version: 0.0.3
Summary: Python package for using the discord-user-history service.
Home-page: https://github.com/IamPekka058/py-discord-user-history
Author: IamPekka058
Author-email: iampekka058@gmail.com
Project-URL: Bug Tracker, https://github.com/IamPekka058/py-discord-user-history/issues
Classifier: Programming Language :: Python :: 3
Classifier: Operating System :: OS Independent
Requires-Python: >=3.6
License-File: LICENSE
